target/__init__.py
target/azure.py
target/plugin.py
target/target.py
pytest_target-0.1.0.dist-info/entry_points.txt
pytest_target-0.1.0.dist-info/WHEEL
pytest_target-0.1.0.dist-info/METADATA
pytest_target-0.1.0.dist-info/RECORD
